sca/__init__.py
sca/sca.py
scafold/__init__.py
scafold/sca.py
scafold-1.0.0.dev3.dist-info/DESCRIPTION.rst
scafold-1.0.0.dev3.dist-info/METADATA
scafold-1.0.0.dev3.dist-info/RECORD
scafold-1.0.0.dev3.dist-info/WHEEL
scafold-1.0.0.dev3.dist-info/metadata.json
scafold-1.0.0.dev3.dist-info/top_level.txt
scanalysis/SCAnalysis.py
scanalysis/__init__.py
