Metadata-Version: 2.0
Name: scafold
Version: 1.0.0.dev3
Summary: A Python implementatino of the SCA method
Home-page: UNKNOWN
Author: Anran Tang
Author-email: at052014@mymail.pomona.edu
License: Apache2
Platform: UNKNOWN
Requires-Dist: IPython (>=4.2)
Requires-Dist: biopython
Requires-Dist: ipywidgets (>=7.0)
Requires-Dist: nglview (>=1.0)
Requires-Dist: numpy
Requires-Dist: plotly
Requires-Dist: scikit-bio
Requires-Dist: scikit-learn
Requires-Dist: scipy
